osjupyter/__init__.py
osjupyter/js/osjupyter/connected_icon.svg
osjupyter/js/osjupyter/disconnected_icon.svg
osjupyter/js/osjupyter/main.js
osjupyter/js/osjupyter/style.css
osjupyter-2.0.1.dist-info/LICENSE.txt
osjupyter-2.0.1.dist-info/METADATA
osjupyter-2.0.1.dist-info/WHEEL
osjupyter-2.0.1.dist-info/top_level.txt
osjupyter-2.0.1.dist-info/RECORD
